rule34_cli/__init__.py
rule34_cli/__main__.py
rule34_cli-0.1.dist-info/METADATA
rule34_cli-0.1.dist-info/WHEEL
rule34_cli-0.1.dist-info/entry_points.txt
rule34_cli-0.1.dist-info/top_level.txt
rule34_cli-0.1.dist-info/RECORD
