Metadata-Version: 2.1
Name: rule34-cli
Version: 0.1
Summary: A command-line tool for searching images from rule34.xxx
Home-page: https://github.com/Lempa21/Rule34-CLI
Author: Lempa
Author-email: mempa1peu@gmail.com
Classifier: Programming Language :: Python :: 3
Classifier: License :: OSI Approved :: MIT License
Classifier: Operating System :: OS Independent
Requires-Python: >=3.6
Requires-Dist: click
Requires-Dist: requests
Requires-Dist: rich
